pyne.py
setup.py
PyNE.egg-info/PKG-INFO
PyNE.egg-info/SOURCES.txt
PyNE.egg-info/dependency_links.txt
PyNE.egg-info/top_level.txt