Metadata-Version: 1.1
Name: PyNE
Version: 0.1.0
Summary: A process networking library.
Home-page: https://github.com/jordanhalterman/pyne
Author: Jordan Halterman
Author-email: jordan.halterman@gmail.com
License: UNKNOWN
Keywords: pyne,processing,multiprocessing,queue
Platform: UNKNOWN
Classifier: Development Status :: 3 - Alpha
Classifier: Environment :: Console
Classifier: Intended Audience :: Developers
Classifier: Operating System :: OS Independent
Classifier: Programming Language :: Python
Classifier: Programming Language :: Python :: 2.5
Classifier: Programming Language :: Python :: 2.6
Classifier: Programming Language :: Python :: 2.7
Classifier: Programming Language :: PHP
Classifier: Natural Language :: English
Classifier: Topic :: Software Development :: Libraries :: Python Modules
